shaplh-1.1.9.dist-info/METADATA
shaplh-1.1.9.dist-info/WHEEL
shaplh/__init__.py
shaplh/shaplh.cpython-37m-x86_64-linux-gnu.so
shaplh-1.1.9.dist-info/RECORD
